apexmq/__init__.py
apexmq/apps.py
apexmq/conf.py
apexmq/consumers.py
apexmq/producers.py
apexmq/managers/__init__.py
apexmq/managers/connection.py
apexmq/managers/consumer.py
apexmq/managers/producer.py
tests/__init__.py
tests/test_conf.py
tests/test_connection_manager.py
tests/test_consumer_manager.py
tests/test_consumers.py
tests/test_producer_manager.py
tests/test_producers.py
apexmq-1.1.0.dist-info/LICENSE
apexmq-1.1.0.dist-info/METADATA
apexmq-1.1.0.dist-info/WHEEL
apexmq-1.1.0.dist-info/top_level.txt
apexmq-1.1.0.dist-info/RECORD
