Metadata-Version: 2.2
Name: apexmq
Version: 1.1.0
Summary: A developer-friendly library for integrating RabbitMQ with Django applications, enabling seamless message queuing, automated consumer registration, and simplified communication between microservices. ApexMQ is designed to streamline asynchronous messaging for Django projects, allowing developers to focus on business logic rather than managing connections and queues.
Home-page: https://github.com/apexkv/apexmq
Author: Kavindu Harshitha
Author-email: kavindu@apexkv.com
License: Custom License
Classifier: Programming Language :: Python :: 3
Classifier: Framework :: Django
Classifier: License :: Other/Proprietary License
Classifier: Operating System :: OS Independent
Requires-Python: >=3.6
License-File: LICENSE
Requires-Dist: pika>=1.1.0
Requires-Dist: django>=3.0.0
Dynamic: author
Dynamic: author-email
Dynamic: classifier
Dynamic: description
Dynamic: description-content-type
Dynamic: home-page
Dynamic: license
Dynamic: requires-dist
Dynamic: requires-python
Dynamic: summary
